{"city":"Madrid","college":"Universidad Politécnica de Madrid"}
{"city":"Barcelona","college":"Facultat d'informatica de Barcelona"}
{"city":"Barcelona","college":"EETAC Castelldefels"}
{"city":"Barcelona","college":"Universitat Pompeu Fabra"}
{"city":"Barcelona","college":"Universitat de Barcelona"}
{"city":"Madrid","college":"Universidad Rey Juan Carlos"}
{"city":"Madrid","college":"Universidad Complutense de Madrid"}
{"city":"Madrid","college":"Universidad Europea de Madrid"}
{"city":"Bruselas","college":"Catholic University of Leuven"}
{"city":"Bruselas","college":"Universite Libre de Bruxelles"}
{"city":"Bruselas","college":"Universite Saint-Louis-Bruxelles"}
{"city":"Londres","college":"University of Oxford London"}
{"city":"Londres","college":"University of Cambridge London"}
{"city":"Londres","college":"University College London"}
{"city":"Londres","college":"University of Manchester London"}
{"city":"Estocolmo","college":"Stockholms universitet Estocolmo"}
{"city":"Estocolmo","college":"Kungliga Tekniska högskolan"}
{"city":"Estocolmo","college":"Handelshögskolan i Stockholm"}
{"city":"Munich","college":" Ludwig-Maximilians-Universität München"}
{"city":"Munich","college":"Technische Universität München"}
{"city":"Munich","college":"Universitat der Bundeswehr Munchen"}
{"city":"Munich","college":"Munich Business School"}
{"city":"Berlin","college":"Freie Universität Berlin"}
{"city":"Berlin","college":"Technische Universität Berlin"}
{"city":"Berlin","college":"Technische Fachhochschule Berlin"}
{"city":"Milan","college":"Politecnico di Milano"}
{"city":"Milan","college":"Università degli Studi di Milano"}
{"city":"Milan","college":" Università degli Studi di Milano - Bicocca"}
{"city":"Lisboa","college":"  Universidade Nova de Lisboa"}
{"city":"Lisboa","college":" Universidade Tecnica de Lisboa"}
{"city":"Lisboa","college":" Universidade de Lisboa"}
{"city":"Lisboa","college":" Universidade Catolica Portuguesa"}
